{
  "chart_id": "wdi__SH.STA.WAST",
  "title": "Prevalence of wasting, weight for height (% of children under 5)",
  "category": "Health",
  "sources": "wdi",
  "n_rows": 90,
  "year_range": [
    "1984",
    "2022"
  ],
  "countries": [
    "ARG",
    "DEU",
    "GBR",
    "GRC",
    "IRN",
    "KOR",
    "NLD",
    "PRT",
    "RUS",
    "SAU",
    "TUR",
    "USA",
    "VEN"
  ],
  "citations": [
    {
      "source_org": "World Bank, World Development Indicators",
      "source_url": "https://data.worldbank.org/indicator/SH.STA.WAST.ZS",
      "access_date": "2026-07-13",
      "time_range": ""
    }
  ],
  "category_fa": "سلامت",
  "title_fa": "شیوع لاغری، وزن به قد (درصد از کودکان زیر 5 سال)"
}
