{
  "chart_id": "wdi__TM.TAX.TCOM.SM.AR",
  "title": "Tariff rate, applied, simple mean, primary products",
  "category": "Trade (Imports)",
  "sources": "wdi",
  "n_rows": 408,
  "year_range": [
    "1988",
    "2022"
  ],
  "countries": [
    "ARG",
    "DEU",
    "ESP",
    "FRA",
    "GBR",
    "GRC",
    "IRN",
    "ITA",
    "KOR",
    "NLD",
    "PRT",
    "RUS",
    "SAU",
    "SWE",
    "TUR",
    "USA",
    "VEN"
  ],
  "citations": [
    {
      "source_org": "World Bank, World Development Indicators",
      "source_url": "https://data.worldbank.org/indicator/TM.TAX.TCOM.SM.AR.ZS",
      "access_date": "2026-07-13",
      "time_range": ""
    }
  ],
  "category_fa": "تجارت (واردات)",
  "title_fa": "نرخ تعرفه، اعمال‌شده، میانگین ساده، محصولات اولیه (درصد)"
}