{
  "chart_id": "wdi__EG.CFT.ACCS",
  "title": "Access to clean fuels and technologies for cooking (% of population)",
  "category": "Energy",
  "sources": "wdi",
  "n_rows": 264,
  "year_range": [
    "2000",
    "2023"
  ],
  "countries": [
    "ARG",
    "ESP",
    "IRN",
    "IRQ",
    "ITA",
    "KOR",
    "RUS",
    "SAU",
    "TUR",
    "USA",
    "VEN"
  ],
  "citations": [
    {
      "source_org": "World Bank, World Development Indicators",
      "source_url": "https://data.worldbank.org/indicator/EG.CFT.ACCS.ZS",
      "access_date": "2026-07-13",
      "time_range": ""
    }
  ],
  "category_fa": "انرژی",
  "title_fa": "دسترسی به سوخت‌ها و فناوری‌های پاک برای پخت‌وپز (درصد از جمعیت)"
}