{
  "chart_id": "faostat__Raw milk of buffalo__production__production",
  "title": "Raw milk of buffalo, production (t)",
  "category": "Agriculture Production",
  "sources": "faostat-qcl",
  "n_rows": 397,
  "year_range": [
    "1961",
    "2024"
  ],
  "countries": [
    "ESP",
    "IRN",
    "IRQ",
    "ITA",
    "TUR",
    "VEN"
  ],
  "citations": [
    {
      "source_org": "FAO, FAOSTAT",
      "source_url": "https://www.fao.org/faostat/en/#data/QCL",
      "access_date": "2026-07-13",
      "time_range": ""
    }
  ],
  "category_fa": "تولید کشاورزی",
  "title_fa": "تولید شیر خام گاومیش (تن)"
}