[
 {
  "law_id": "1d1b45a01825",
  "law_date": "2001",
  "law_title_fa": "قانون الحاق یک ماده به قانون نحوه انتشار اوراق مشارکت با اصلاحات و الحاقات بعدی",
  "n_charts": "2",
  "source_path": "/Users/rohamhosseini/Documents/scraper simple/laws_clean/general_laws/4372542169033758889_4372542169033758889.txt"
 },
 {
  "law_id": "360c547b51aa",
  "law_date": "2014",
  "law_title_fa": "خروج شركتهاي توزيع نيروي برق از پيوست شم ... ياست هاي كلي اصل چهل و چهارم قانون اساسي",
  "n_charts": "2",
  "source_path": "/Users/rohamhosseini/Documents/scraper simple/laws_clean/Aeen-Nameh/خروج_شركتهاي_توزيع_نيروي_برق_از_پيوست_شم_..._ياست_هاي_كلي_اصل_چهل_و_چهارم_قانون_اساسي_7365015583555108810.txt"
 },
 {
  "law_id": "2fcde6f75dc2",
  "law_date": "2003",
  "law_title_fa": "تصويب نامه راجع به جداول حقوق ورودي پيوس ... نامه اجرايي قانون مقررات صادرات و واردات",
  "n_charts": "2",
  "source_path": "/Users/rohamhosseini/Documents/scraper simple/laws_clean/Aeen-Nameh/تصويب_نامه_راجع_به_جداول_حقوق_ورودي_پيوس_..._نامه_اجرايي_قانون_مقررات_صادرات_و_واردات_6555324846110327100.txt"
 },
 {
  "law_id": "7684eadf9c75",
  "law_date": "2008",
  "law_title_fa": "اتخاذ تصميماتي در خصوص جداول پيوست آيين نامه اجرايي قانون مقررات صادرات و واردات",
  "n_charts": "2",
  "source_path": "/Users/rohamhosseini/Documents/scraper simple/laws_clean/Aeen-Nameh/اتخاذ_تصميماتي_در_خصوص_جداول_پيوست_آيين_نامه_اجرايي_قانون_مقررات_صادرات_و_واردات_7072600592472289637.txt"
 },
 {
  "law_id": "e335e6cabaff",
  "law_date": "2006",
  "law_title_fa": "قانون موافقتنامه تجارت ترجيحي بين دولت ج ... امي پاكستان و پروتكل اصلاحي برخي مواد آن",
  "n_charts": "2",
  "source_path": "/Users/rohamhosseini/Documents/scraper simple/laws_clean/general_laws/قانون_موافقتنامه_تجارت_ترجيحي_بين_دولت_ج_..._امي_پاكستان_و_پروتكل_اصلاحي_برخي_مواد_آن_6369881020926024337.txt"
 },
 {
  "law_id": "45c1aa11a634",
  "law_date": "1997",
  "law_title_fa": "قانون اصلاح برخي از مواد قانون نحوه واگذ ... ي و متعلق به دولت به ايثارگران و كارگران",
  "n_charts": "2",
  "source_path": "/Users/rohamhosseini/Documents/scraper simple/laws_clean/general_laws/قانون_اصلاح_برخي_از_مواد_قانون_نحوه_واگذ_..._ي_و_متعلق_به_دولت_به_ايثارگران_و_كارگران_9306068897028734970.txt"
 },
 {
  "law_id": "aec35c63e637",
  "law_date": "1986",
  "law_title_fa": "اصلاحيه ماده 53 آيين نامه اجرايي قانون مقررات صادرات و واردات سال 65",
  "n_charts": "2",
  "source_path": "/Users/rohamhosseini/Documents/scraper simple/laws_clean/Aeen-Nameh/_اصلاحيه_ماده_53_آيين_نامه_اجرايي_قانون_مقررات_صادرات_و_واردات_سال_65_3824787384469354550.txt"
 },
 {
  "law_id": "05812a24dad6",
  "law_date": "1984",
  "law_title_fa": "آيين نامه استخراج و فروش معادن توسط بخش خصوصي",
  "n_charts": "2",
  "source_path": "/Users/rohamhosseini/Documents/scraper simple/laws_clean/Aeen-Nameh/_آيين_نامه_استخراج_و_فروش_معادن_توسط_بخش_خصوصي_10780570164633202650.txt"
 },
 {
  "law_id": "cbfdb25886d6",
  "law_date": "2000",
  "law_title_fa": "آيين نامه  نحوه  تعيين  و تشخيص  معادن  بزرگ  و كوچك",
  "n_charts": "2",
  "source_path": "/Users/rohamhosseini/Documents/scraper simple/laws_clean/Aeen-Nameh/آيين_نامه__نحوه__تعيين__و_تشخيص__معادن__بزرگ__و_كوچك_8892581381664021635.txt"
 },
 {
  "law_id": "f8dc53c768d9",
  "law_date": "2012",
  "law_title_fa": "آيين نامه ماده  13  قانون توسعه ابزارها  ... ي كلي اصل  44  قانون اساسي - مصوب - 1388",
  "n_charts": "2",
  "source_path": "/Users/rohamhosseini/Documents/scraper simple/laws_clean/Aeen-Nameh/آيين_نامه_ماده__13__قانون_توسعه_ابزارها__..._ي_كلي_اصل__44__قانون_اساسي_-_مصوب_-_1388_636471002640606093.txt"
 },
 {
  "law_id": "478e7a6f69f7",
  "law_date": "2011",
  "law_title_fa": "آيين نامه اجرايي ماده   14   قانون توسعه ... راي سياست هاي كلي اصل   44   قانون اساسي",
  "n_charts": "2",
  "source_path": "/Users/rohamhosseini/Documents/scraper simple/laws_clean/Aeen-Nameh/آيين_نامه_اجرايي_ماده___14___قانون_توسعه_..._راي_سياست_هاي_كلي_اصل___44___قانون_اساسي_3472018483380900768.txt"
 },
 {
  "law_id": "57f6a8c265b0",
  "law_date": "2003",
  "law_title_fa": "قانون اصلاح ماده  60  و جدول شماره  2  ق ... امي ايران و قانون بودجه سال 1382 كل كشور",
  "n_charts": "2",
  "source_path": "/Users/rohamhosseini/Documents/scraper simple/laws_clean/general_laws/قانون_اصلاح_ماده__60__و_جدول_شماره__2__ق_..._امي_ايران_و_قانون_بودجه_سال_1382_كل_كشور_14918116952717102065.txt"
 },
 {
  "law_id": "8ba852a1085b",
  "law_date": "1980",
  "law_title_fa": "لایحه قانونی راجع به استفاده از مبلغ ۲۰ میلیارد ریال حاصل از قطع کمک دولت به قیمت گوشت مصرفی تهران و اصفهان جهت بهبود امر دامپروری و احیای دامپروری سنتی روستائی با اصلاحات و الحاقات بعدی",
  "n_charts": "2",
  "source_path": "/Users/rohamhosseini/Documents/scraper simple/laws_clean/general_laws/11311277616530975682_11311277616530975682.txt"
 },
 {
  "law_id": "4d7d6955ca60",
  "law_date": "2015",
  "law_title_fa": "آيين نامه اجرايي ماده  25  قانون رفع موانع توليد رقابت پذير و ارتقاي نظام مالي كشور",
  "n_charts": "2",
  "source_path": "/Users/rohamhosseini/Documents/scraper simple/laws_clean/Aeen-Nameh/آيين_نامه_اجرايي_ماده__25__قانون_رفع_موانع_توليد_رقابت_پذير_و_ارتقاي_نظام_مالي_كشور_3038032540139124197.txt"
 },
 {
  "law_id": "1f1cdcf5f33b",
  "law_date": "1969",
  "law_title_fa": "قانون تشكيل سازمانهاي عمران كشاورزي و توسعه دامپروري",
  "n_charts": "2",
  "source_path": "/Users/rohamhosseini/Documents/scraper simple/laws_clean/general_laws/_قانون_تشكيل_سازمانهاي_عمران_كشاورزي_و_توسعه_دامپروري_10105225450147286890.txt"
 },
 {
  "law_id": "d50f1c9674c7",
  "law_date": "2001",
  "law_title_fa": "قانون اجازه منظور نمودن عوارض توسعه تلفن ... اب افزايش سرمايه دولت در شركتهاي مخابرات",
  "n_charts": "2",
  "source_path": "/Users/rohamhosseini/Documents/scraper simple/laws_clean/general_laws/قانون_اجازه_منظور_نمودن_عوارض_توسعه_تلفن_..._اب_افزايش_سرمايه_دولت_در_شركتهاي_مخابرات_10637051990501081687.txt"
 },
 {
  "law_id": "eb7d9d2ecf89",
  "law_date": "1965",
  "law_title_fa": "قانون راجع باجازه مبادله و اجراي پنج فقره قرارداد نفت",
  "n_charts": "2",
  "source_path": "/Users/rohamhosseini/Documents/scraper simple/laws_clean/general_laws/قانون_راجع_باجازه_مبادله_و_اجراي_پنج_فقره_قرارداد_نفت_12539727909862938924.txt"
 },
 {
  "law_id": "2ea2992acd52",
  "law_date": "2017",
  "law_title_fa": "آيين نامه اجرايي تبصره  35  و رديف  1  ج ... قانون اصلاح قانون بودجه سال 1395 كل كشور",
  "n_charts": "2",
  "source_path": "/Users/rohamhosseini/Documents/scraper simple/laws_clean/Aeen-Nameh/آيين_نامه_اجرايي_تبصره__35__و_رديف__1__ج_..._قانون_اصلاح_قانون_بودجه_سال_1395_كل_كشور_2809902551737319259.txt"
 },
 {
  "law_id": "78d061997227",
  "law_date": "2001",
  "law_title_fa": "آيين نامه  اجرايي  بند الف  تبصره  27 قانون  بودجه  سال  1380كل  كشور",
  "n_charts": "2",
  "source_path": "/Users/rohamhosseini/Documents/scraper simple/laws_clean/Aeen-Nameh/آيين_نامه__اجرايي__بند_الف__تبصره__27_قانون__بودجه__سال__1380كل__كشور_1569265865843331640.txt"
 },
 {
  "law_id": "b1d85a9e05b0",
  "law_date": "1995",
  "law_title_fa": "آيين نامه اجرايي قانون نحوه واگذاري سهام دولتي و متعلق به دولت به ايثارگران و كارگران",
  "n_charts": "2",
  "source_path": "/Users/rohamhosseini/Documents/scraper simple/laws_clean/Aeen-Nameh/آيين_نامه_اجرايي_قانون_نحوه_واگذاري_سهام_دولتي_و_متعلق_به_دولت_به_ايثارگران_و_كارگران_13295751431535965465.txt"
 },
 {
  "law_id": "2142825f5b4d",
  "law_date": "2010",
  "law_title_fa": "ضوابط محاسبه سهام شناور آزاد موضوع ماده  ... ل اجراي سياست هاي كلي اصل 44 قانون اساسي",
  "n_charts": "2",
  "source_path": "/Users/rohamhosseini/Documents/scraper simple/laws_clean/Aeen-Nameh/ضوابط_محاسبه_سهام_شناور_آزاد_موضوع_ماده__..._ل_اجراي_سياست_هاي_كلي_اصل_44_قانون_اساسي_6264307217643483456.txt"
 },
 {
  "law_id": "8ebf737ce68f",
  "law_date": "2014",
  "law_title_fa": "الحاق تبصره به بند  2  ماده  10  آيين نامه اجرايي قانون مقررات صادرات و واردات",
  "n_charts": "2",
  "source_path": "/Users/rohamhosseini/Documents/scraper simple/laws_clean/Aeen-Nameh/الحاق_تبصره_به_بند__2__ماده__10__آيين_نامه_اجرايي_قانون_مقررات_صادرات_و_واردات_424123100945393656.txt"
 },
 {
  "law_id": "d8b4dd8686d1",
  "law_date": "2015",
  "law_title_fa": "اصلاح ماده  11  آيين نامه اجرايي قانون مقررات صادرات و واردات",
  "n_charts": "2",
  "source_path": "/Users/rohamhosseini/Documents/scraper simple/laws_clean/Aeen-Nameh/اصلاح_ماده__11__آيين_نامه_اجرايي_قانون_مقررات_صادرات_و_واردات_5166512543779858111.txt"
 },
 {
  "law_id": "c70be89097fd",
  "law_date": "1966",
  "law_title_fa": "قانون اجازه  تحصيل وام  از بانك صادرات   ... رفع نيازمنديهاي شركت هواپيمائي ملي ايران",
  "n_charts": "2",
  "source_path": "/Users/rohamhosseini/Documents/scraper simple/laws_clean/general_laws/قانون_اجازه__تحصيل_وام__از_بانك_صادرات___..._رفع_نيازمنديهاي_شركت_هواپيمائي_ملي_ايران_15494827468651590588.txt"
 },
 {
  "law_id": "fffd3a1dac58",
  "law_date": "1982",
  "law_title_fa": "قانون متمم بودجه سال 1361",
  "n_charts": "2",
  "source_path": "/Users/rohamhosseini/Documents/scraper simple/laws_clean/general_laws/قانون_متمم_بودجه_سال_1361_10361582797485502900.txt"
 }
]