{
  "chart_id": "pahlavi__bank_deposits_private_sector_1963_70",
  "title": "Private-Sector Bank Deposits by Type (Sight/Saving/Time), FY1963/64-1969/70",
  "category": "Financial Sector (Monetary)",
  "sources": "pahlavi-era-primary-extraction",
  "n_rows": 135,
  "year_range": [
    "1964",
    "1970"
  ],
  "countries": [
    "IRN"
  ],
  "citations": [
    {
      "source_org": "International Bank for Reconstruction and Development (World Bank), companion table to Table 6.1 'Monetary Survey' in the same report section, both ultimately sourced from Bank Markazi Iran (Central Bank of Iran) data",
      "source_url": "https://search.worldbank.org/api/v3/wds (World Bank Documents & Reports API)",
      "access_date": "2026-07-13",
      "time_range": "",
      "match_confidence": "fuzzy:5tok:wb1971-bank-deposits-private-sector-1963-1970"
    }
  ],
  "category_fa": "بخش مالی (پولی)",
  "title_fa": "سپرده‌های بانکی بخش خصوصی به تفکیک نوع (دیداری/پس‌انداز/مدت‌دار)، سال مالی 1963/64-1969/70"
}